json_tabulator/__init__.py
json_tabulator/api.py
json_tabulator/exceptions.py
json_tabulator/expression.py
json_tabulator/parser.py
json_tabulator/query.py
json_tabulator-0.6.1.dist-info/LICENSE
json_tabulator-0.6.1.dist-info/METADATA
json_tabulator-0.6.1.dist-info/WHEEL
json_tabulator-0.6.1.dist-info/RECORD
