Metadata-Version: 2.1
Name: json_tabulator
Version: 0.6.1
Summary: Simple query language to extract tables from JSON.
License: MIT
Author: Matthias Ossadnik
Author-email: ossadnik.matthias@gmail.com
Requires-Python: >=3.9,<4.0
Classifier: Development Status :: 4 - Beta
Classifier: License :: OSI Approved :: MIT License
Classifier: Programming Language :: Python :: 3
Classifier: Programming Language :: Python :: 3.9
Classifier: Programming Language :: Python :: 3.10
Classifier: Programming Language :: Python :: 3.11
Classifier: Programming Language :: Python :: 3.12
Classifier: Programming Language :: Python :: 3.13
Requires-Dist: parsy (>=2.1,<3.0)
Project-URL: homepage, https://github.com/mossadnik/json_tabulator
